ExtremePluginManager/__init__.py
ExtremePluginManager/constants.py
ExtremePluginManager/extreme_plugin_manager.py
ExtremePluginManager/strings.py
ExtremePluginManager/background/__init__.py
ExtremePluginManager/background/background_task.py
ExtremePluginManager/background/base_thread.py
ExtremePluginManager/background/delayed_task.py
ExtremePluginManager/background/interval_task.py
ExtremePluginManager/converter/__init__.py
ExtremePluginManager/converter/directory.py
ExtremePluginManager/converter/zip.py
ExtremePluginManager/plugin/__init__.py
ExtremePluginManager/plugin/base_plugin.py
ExtremePluginManager/plugin/directory_plugin.py
ExtremePluginManager/plugin/zip_file_plugin.py
ExtremePluginManager-1.1.3.dist-info/LICENSE
ExtremePluginManager-1.1.3.dist-info/METADATA
ExtremePluginManager-1.1.3.dist-info/WHEEL
ExtremePluginManager-1.1.3.dist-info/top_level.txt
ExtremePluginManager-1.1.3.dist-info/RECORD
