Metadata-Version: 2.1
Name: ExtremePluginManager
Version: 1.1.3
Summary: A powerful library for managing plugins in your Python application.
Home-page: https://github.com/CPSuperstore/ExtremePluginManager
Author: CPSuperstore
Author-email: cpsuperstoreinc@gmail.com
License: MIT Licence
Project-URL: Bug Tracker, https://github.com/CPSuperstore/ExtremePluginManager/issues
Keywords: Plugin,Manager
Classifier: Development Status :: 4 - Beta
Classifier: Intended Audience :: Developers
Classifier: Environment :: Plugins
Classifier: Intended Audience :: Developers
Classifier: License :: OSI Approved :: MIT License
Classifier: Natural Language :: English
Classifier: Programming Language :: Python :: 3
Classifier: Topic :: Desktop Environment
Classifier: Topic :: Games/Entertainment
Classifier: Topic :: Software Development
Classifier: Topic :: Utilities
License-File: LICENSE
